setup.py
speakin_long_vec_sdk/__init__.py
speakin_long_vec_sdk/api_client.py
speakin_long_vec_sdk/configuration.py
speakin_long_vec_sdk/rest.py
speakin_long_vec_sdk.egg-info/PKG-INFO
speakin_long_vec_sdk.egg-info/SOURCES.txt
speakin_long_vec_sdk.egg-info/dependency_links.txt
speakin_long_vec_sdk.egg-info/requires.txt
speakin_long_vec_sdk.egg-info/top_level.txt
speakin_long_vec_sdk/apis/__init__.py
speakin_long_vec_sdk/apis/longreleasev_api.py
speakin_long_vec_sdk/models/__init__.py
speakin_long_vec_sdk/models/voiceprint_rawcompare_req.py
test/__init__.py
test/test_longreleasev_api.py
test/test_voiceprint_rawcompare_req.py