Metadata-Version: 1.0
Name: speakin-long-vec-sdk
Version: 1.0.0
Summary: long_release_v1
Home-page: UNKNOWN
Author: UNKNOWN
Author-email: UNKNOWN
License: UNKNOWN
Keywords: Swagger,long_release_v1
Platform: UNKNOWN
